LICENSE
MANIFEST.in
README.rst
setup.py
django_hstsmiddleware/__init__.py
django_hstsmiddleware/middleware.py
django_hstsmiddleware/models.py
django_hstsmiddleware/patch.py
django_hstsmiddleware/tests.py
django_hstsmiddleware.egg-info/PKG-INFO
django_hstsmiddleware.egg-info/SOURCES.txt
django_hstsmiddleware.egg-info/dependency_links.txt
django_hstsmiddleware.egg-info/requires.txt
django_hstsmiddleware.egg-info/top_level.txt
django_hstsmiddleware.egg-info/zip-safe