Metadata-Version: 1.0
Name: django-hstsmiddleware
Version: 1.0
Summary: Implement HSTS to force the use of HTTPS.
Home-page: http://bitbucket.org/trustcentric/django-hstsmiddleware/
Author: TrustCentric
Author-email: admin@trustcentric.com
License: UNKNOWN
Platform: UNKNOWN
Classifier: Development Status :: 5 - Production/Stable
Classifier: Environment :: Web Environment
Classifier: Framework :: Django
Classifier: License :: OSI Approved :: BSD License
Classifier: Operating System :: OS Independent
Classifier: Programming Language :: Python
